Workbook

Sheet 📊 Dashboard
B2: 💼 CONTROLE FINANCEIRO MEI
B3: Os valores atualizam automaticamente conforme você lança ▶
B5: 📈 RESUMO DO ANO
B6: 💰 Total Receitas no Ano | C6: ='📈 Anual'!C17 -> 0
B7: 💸 Total Despesas no Ano | C7: ='📈 Anual'!D17 -> 0
B8: ✅ Lucro Total no Ano | C8: ='📈 Anual'!E17 -> 0
B10: 📏 LIMITE MEI
B11: 📈 Faturado no Ano | C11: ='📈 Anual'!C17 -> 0
B12: 📏 Limite Configurado | C12: ='⚙️ Config'!$C$4 -> 81000
B13: 📉 Saldo Disponível | C13: ='⚙️ Config'!$C$4-'📈 Anual'!C17 -> 81000
B14: 📊 % do Limite Usado | C14: ='📈 Anual'!C17/'⚙️ Config'!$C$4 -> 0
B16: 🔔 ALERTAS
B17: =IF('📈 Anual'!C17>'⚙️ Config'!$C$4*0.9,"🚨 ATENÇÃO: Acima de 90% do limite MEI!","✅ Faturamento dentro do limite") -> ✅ Faturamento dentro do limite
B18: 📅 DAS vence dia 20 do mês seguinte
B20: 📋 COMO USAR
B21: 1️⃣ Abra a aba do mês atual (Jan, Fev...)
B22: 2️⃣ Selecione Receita ou Despesa no Tipo
B23: 3️⃣ Escreva uma descrição e o valor
B24: 4️⃣ Totais aparecem no Anual automaticamente
B25: 5️⃣ Confira o DAS e pague até dia 20
B26: ⚙️ Limite MEI mudou? Altere na aba ⚙️ Config
B27: GERAR DAS .gov

Sheet Jan
B2: 📝 LANÇAMENTOS — JAN
B3: 💰 RECEITAS | C3: =SUMIF(B8:B207,"Receita",D8:D207) -> 0
B4: 💸 DESPESAS | C4: =SUMIF(B8:B207,"Despesa",D8:D207) -> 0
B5: ✅ LUCRO | C5: =C3-C4 -> 0
B7: Tipo | C7: Descrição | D7: Valor (R$)
B209: ℹ️ Selecione Tipo → escreva Descrição → digite o Valor

Sheet Fev
B2: 📝 LANÇAMENTOS — FEV
B3: 💰 RECEITAS | C3: =SUMIF(B8:B207,"Receita",D8:D207) -> 0
B4: 💸 DESPESAS | C4: =SUMIF(B8:B207,"Despesa",D8:D207) -> 0
B5: ✅ LUCRO | C5: =C3-C4 -> 0
B7: Tipo | C7: Descrição | D7: Valor (R$)
B209: ℹ️ Selecione Tipo → escreva Descrição → digite o Valor

Sheet Mar
B2: 📝 LANÇAMENTOS — MAR
B3: 💰 RECEITAS | C3: =SUMIF(B8:B207,"Receita",D8:D207) -> 0
B4: 💸 DESPESAS | C4: =SUMIF(B8:B207,"Despesa",D8:D207) -> 0
B5: ✅ LUCRO | C5: =C3-C4 -> 0
B7: Tipo | C7: Descrição | D7: Valor (R$)
B209: ℹ️ Selecione Tipo → escreva Descrição → digite o Valor

Sheet Abr
B2: 📝 LANÇAMENTOS — ABR
B3: 💰 RECEITAS | C3: =SUMIF(B8:B207,"Receita",D8:D207) -> 0
B4: 💸 DESPESAS | C4: =SUMIF(B8:B207,"Despesa",D8:D207) -> 0
B5: ✅ LUCRO | C5: =C3-C4 -> 0
B7: Tipo | C7: Descrição | D7: Valor (R$)
B209: ℹ️ Selecione Tipo → escreva Descrição → digite o Valor

Sheet Mai
B2: 📝 LANÇAMENTOS — MAI
B3: 💰 RECEITAS | C3: =SUMIF(B8:B207,"Receita",D8:D207) -> 0
B4: 💸 DESPESAS | C4: =SUMIF(B8:B207,"Despesa",D8:D207) -> 0
B5: ✅ LUCRO | C5: =C3-C4 -> 0
B7: Tipo | C7: Descrição | D7: Valor (R$)
B209: ℹ️ Selecione Tipo → escreva Descrição → digite o Valor

Sheet Jun
B2: 📝 LANÇAMENTOS — JUN
B3: 💰 RECEITAS | C3: =SUMIF(B8:B207,"Receita",D8:D207) -> 0
B4: 💸 DESPESAS | C4: =SUMIF(B8:B207,"Despesa",D8:D207) -> 0
B5: ✅ LUCRO | C5: =C3-C4 -> 0
B7: Tipo | C7: Descrição | D7: Valor (R$)
B209: ℹ️ Selecione Tipo → escreva Descrição → digite o Valor

Sheet Jul
B2: 📝 LANÇAMENTOS — JUL
B3: 💰 RECEITAS | C3: =SUMIF(B8:B207,"Receita",D8:D207) -> 0
B4: 💸 DESPESAS | C4: =SUMIF(B8:B207,"Despesa",D8:D207) -> 0
B5: ✅ LUCRO | C5: =C3-C4 -> 0
B7: Tipo | C7: Descrição | D7: Valor (R$)
B209: ℹ️ Selecione Tipo → escreva Descrição → digite o Valor

Sheet Ago
B2: 📝 LANÇAMENTOS — AGO
B3: 💰 RECEITAS | C3: =SUMIF(B8:B207,"Receita",D8:D207) -> 0
B4: 💸 DESPESAS | C4: =SUMIF(B8:B207,"Despesa",D8:D207) -> 0
B5: ✅ LUCRO | C5: =C3-C4 -> 0
B7: Tipo | C7: Descrição | D7: Valor (R$)
B209: ℹ️ Selecione Tipo → escreva Descrição → digite o Valor

Sheet Set
B2: 📝 LANÇAMENTOS — SET
B3: 💰 RECEITAS | C3: =SUMIF(B8:B207,"Receita",D8:D207) -> 0
B4: 💸 DESPESAS | C4: =SUMIF(B8:B207,"Despesa",D8:D207) -> 0
B5: ✅ LUCRO | C5: =C3-C4 -> 0
B7: Tipo | C7: Descrição | D7: Valor (R$)
B209: ℹ️ Selecione Tipo → escreva Descrição → digite o Valor

Sheet Out
B2: 📝 LANÇAMENTOS — OUT
B3: 💰 RECEITAS | C3: =SUMIF(B8:B207,"Receita",D8:D207) -> 0
B4: 💸 DESPESAS | C4: =SUMIF(B8:B207,"Despesa",D8:D207) -> 0
B5: ✅ LUCRO | C5: =C3-C4 -> 0
B7: Tipo | C7: Descrição | D7: Valor (R$)
B209: ℹ️ Selecione Tipo → escreva Descrição → digite o Valor

Sheet Nov
B2: 📝 LANÇAMENTOS — NOV
B3: 💰 RECEITAS | C3: =SUMIF(B8:B207,"Receita",D8:D207) -> 0
B4: 💸 DESPESAS | C4: =SUMIF(B8:B207,"Despesa",D8:D207) -> 0
B5: ✅ LUCRO | C5: =C3-C4 -> 0
B7: Tipo | C7: Descrição | D7: Valor (R$)
B209: ℹ️ Selecione Tipo → escreva Descrição → digite o Valor

Sheet Dez
B2: 📝 LANÇAMENTOS — DEZ
B3: 💰 RECEITAS | C3: =SUMIF(B8:B207,"Receita",D8:D207) -> 0
B4: 💸 DESPESAS | C4: =SUMIF(B8:B207,"Despesa",D8:D207) -> 0
B5: ✅ LUCRO | C5: =C3-C4 -> 0
B7: Tipo | C7: Descrição | D7: Valor (R$)
B209: ℹ️ Selecione Tipo → escreva Descrição → digite o Valor

Sheet 📈 Anual
B2: 📈 RESUMO ANUAL
B4: Mês | C4: 💰 Receitas | D4: 💸 Despesas | E4: ✅ Lucro
B5: Jan | C5: =Jan!C3 -> 0 | D5: =Jan!C4 -> 0 | E5: =Jan!C5 -> 0
B6: Fev | C6: =Fev!C3 -> 0 | D6: =Fev!C4 -> 0 | E6: =Fev!C5 -> 0
B7: Mar | C7: =Mar!C3 -> 0 | D7: =Mar!C4 -> 0 | E7: =Mar!C5 -> 0
B8: Abr | C8: =Abr!C3 -> 0 | D8: =Abr!C4 -> 0 | E8: =Abr!C5 -> 0
B9: Mai | C9: =Mai!C3 -> 0 | D9: =Mai!C4 -> 0 | E9: =Mai!C5 -> 0
B10: Jun | C10: =Jun!C3 -> 0 | D10: =Jun!C4 -> 0 | E10: =Jun!C5 -> 0
B11: Jul | C11: =Jul!C3 -> 0 | D11: =Jul!C4 -> 0 | E11: =Jul!C5 -> 0
B12: Ago | C12: =Ago!C3 -> 0 | D12: =Ago!C4 -> 0 | E12: =Ago!C5 -> 0
B13: Set | C13: =Set!C3 -> 0 | D13: =Set!C4 -> 0 | E13: =Set!C5 -> 0
B14: Out | C14: =Out!C3 -> 0 | D14: =Out!C4 -> 0 | E14: =Out!C5 -> 0
B15: Nov | C15: =Nov!C3 -> 0 | D15: =Nov!C4 -> 0 | E15: =Nov!C5 -> 0
B16: Dez | C16: =Dez!C3 -> 0 | D16: =Dez!C4 -> 0 | E16: =Dez!C5 -> 0
B17: TOTAL ANUAL | C17: =SUM(C5:C16) -> 0 | D17: =SUM(D5:D16) -> 0 | E17: =SUM(E5:E16) -> 0
B19: 🏷️ Faturado no Ano | D19: =C17 -> 0
B20: 📏 Limite MEI | D20: ='⚙️ Config'!$C$4 -> 81000
B21: 📉 Saldo Disponível | D21: ='⚙️ Config'!$C$4-C17 -> 81000
B22: 📊 % do Limite Usado | D22: =C17/'⚙️ Config'!$C$4 -> 0
B24: 📊 DECLARAÇÃO ANUAL — IRPF/DASN
B25: 🏷️ Tipo de Atividade | D25: Serviços
B26: ↳ Opções: Serviços (32%) · Comércio (8%) · Transporte (16%)
B27: 💰 Faturamento Bruto no Ano | D27: =C17 -> 0
B28: ✅ Parcela Isenta | D28: =IF(D25="Serviços",C17*0.32,IF(D25="Transporte",C17*0.16,C17*0.08)) -> 0
B29: 💸 Despesas Comprovadas | D29: =D17 -> 0
B30: ⚠️ Lucro Tributável (IRPF) | D30: =C17-D28-D29 -> 0
B31: ℹ️ Use estes valores para preencher a DASN e a Declaração de IR

Sheet 🧾 DAS
B2: 🧾 CONTROLE DO DAS MENSAL
B4: Mês | C4: 💰 Receita | D4: DAS PAGO
B5: Jan | C5: =Jan!C3 -> 0 | D5: Pendente
B6: Fev | C6: =Fev!C3 -> 0 | D6: Pendente
B7: Mar | C7: =Mar!C3 -> 0 | D7: Pendente
B8: Abr | C8: =Abr!C3 -> 0 | D8: Pendente
B9: Mai | C9: =Mai!C3 -> 0 | D9: Pendente
B10: Jun | C10: =Jun!C3 -> 0 | D10: Pendente
B11: Jul | C11: =Jul!C3 -> 0 | D11: Pendente
B12: Ago | C12: =Ago!C3 -> 0 | D12: Pendente
B13: Set | C13: =Set!C3 -> 0 | D13: Pendente
B14: Out | C14: =Out!C3 -> 0 | D14: Pendente
B15: Nov | C15: =Nov!C3 -> 0 | D15: Pendente
B16: Dez | C16: =Dez!C3 -> 0 | D16: Pendente
B17: TOTAL | C17: =SUM(C5:C16) -> 0
B19: ℹ️ DAS vence todo dia 20 do mês seguinte · Marque como 'Pago' após efetuar o pagamento
C21: GERAR DAS .gov

Sheet ⚙️ Config
B2: ⚙️ CONFIGURAÇÕES DA PLANILHA
B4: 🏷️ Limite Anual MEI (R$) | C4: 81000
B5: ⬆️ Altere o valor acima se o limite MEI mudar. Tudo atualiza automaticamente.
B7: 📌 INFORMAÇÕES
B8: Vencimento DAS | C8: Dia 20 do mês seguinte
B9: Categoria | C9: MEI - Microempreendedor Individual
B11: ⚠️ Não altere outras células desta aba além do Limite Anual MEI
